redocker/__init__.py
redocker/docker.py
redocker/redocker.py
redocker-0.1.3.dist-info/entry_points.txt
redocker-0.1.3.dist-info/WHEEL
redocker-0.1.3.dist-info/METADATA
redocker-0.1.3.dist-info/RECORD
